src/BCDtoSSeg.v
module BCDtoSSeg (
    input [3:0] BCD, 
    output reg [0:6] SSeg, 
    output [3:0] an
  );
  
  assign an = 4'b1110;

  always @ ( * ) begin
    case (BCD)
      4'b0000: SSeg = 7'b0000001; // "0"  
  	  4'b0001: SSeg = 7'b1001111; // "1"  
  	  4'b0010: SSeg = 7'b0010010; // "2" 
  	  4'b0011: SSeg = 7'b0000110; // "3" 
  	  4'b0100: SSeg = 7'b1001100; // "4" 
  	  4'b0101: SSeg = 7'b0100100; // "5" 
  	  4'b0110: SSeg = 7'b0100000; // "6" 
  	  4'b0111: SSeg = 7'b0001111; // "7" 
  	  4'b1000: SSeg = 7'b0000000; // "8"  
  	  4'b1001: SSeg = 7'b0000100; // "9" 
      4'ha: SSeg = 7'b0001000;  
      4'hb: SSeg = 7'b1100000;
      4'hc: SSeg = 7'b0110001;
      4'hd: SSeg = 7'b1000010;
      4'he: SSeg = 7'b0110000;
      4'hf: SSeg = 7'b0111000;
       default: SSeg = 7'b0000000;
    endcase
  end

endmodule

src/BCDtoSSeg_tb.v
`timescale 1ns / 1ps
`include "src/BCDtoSSeg.v"
module tb_BCDtoSSeg();

  reg [3:0] BCD;
  wire [0:6] SSeg;
  wire [3:0] an;

  BCDtoSSeg uut (
    .BCD(BCD),
    .SSeg(SSeg),
    .an(an)
  );

  initial begin
    $dumpfile("tb_BCDtoSSeg.vcd"); 
    $dumpvars(0, tb_BCDtoSSeg);

    // Prueba todos los valores posibles de 4 bits (0 a 15)
    BCD = 4'b0000; #10;
    BCD = 4'b0001; #10;
    BCD = 4'b0010; #10;
    BCD = 4'b0011; #10;
    BCD = 4'b0100; #10;
    BCD = 4'b0101; #10;
    BCD = 4'b0110; #10;
    BCD = 4'b0111; #10;
    BCD = 4'b1000; #10;
    BCD = 4'b1001; #10;
    BCD = 4'ha;    #10;
    BCD = 4'hb;    #10;
    BCD = 4'hc;    #10;
    BCD = 4'hd;    #10;
    BCD = 4'he;    #10;
    BCD = 4'hf;    #10;

    $finish;
  end

endmodule

build/tb_BCDtoSSeg.vcd
$date
	Thu Jun  5 12:22:12 2025
$end
$version
	Icarus Verilog
$end
$timescale
	1ps
$end
$scope module tb_BCDtoSSeg $end
$var wire 4 ! an [3:0] $end
$var wire 7 " SSeg [0:6] $end
$var reg 4 # BCD [3:0] $end
$scope module uut $end
$var wire 4 $ BCD [3:0] $end
$var wire 4 % an [3:0] $end
$var reg 7 & SSeg [0:6] $end
$upscope $end
$upscope $end
$enddefinitions $end
$comment Show the parameter values. $end
$dumpall
$end
#0
$dumpvars
b1 &
b1110 %
b0 $
b0 #
b1 "
b1110 !
$end
#10000
b1001111 "
b1001111 &
b1 #
b1 $
#20000
b10010 "
b10010 &
b10 #
b10 $
#30000
b110 "
b110 &
b11 #
b11 $
#40000
b1001100 "
b1001100 &
b100 #
b100 $
#50000
b100100 "
b100100 &
b101 #
b101 $
#60000
b100000 "
b100000 &
b110 #
b110 $
#70000
b1111 "
b1111 &
b111 #
b111 $
#80000
b0 "
b0 &
b1000 #
b1000 $
#90000
b100 "
b100 &
b1001 #
b1001 $
#100000
b1000 "
b1000 &
b1010 #
b1010 $
#110000
b1100000 "
b1100000 &
b1011 #
b1011 $
#120000
b110001 "
b110001 &
b1100 #
b1100 $
#130000
b1000010 "
b1000010 &
b1101 #
b1101 $
#140000
b110000 "
b110000 &
b1110 #
b1110 $
#150000
b111000 "
b111000 &
b1111 #
b1111 $
